peakrdl_cheader/__about__.py
peakrdl_cheader/__init__.py
peakrdl_cheader/exporter.py
peakrdl_cheader/peakcheader.py
peakrdl_cheader/systemrdl_node_utility_functions.py
peakrdl_cheader/templates/addrmap.h.jinja
peakrdl_cheader/templates/addrmap_field.h.jinja
peakrdl_cheader/templates/addrmap_memory.h.jinja
peakrdl_cheader/templates/addrmap_register.h.jinja
peakrdl_cheader/templates/addrmap_tb.c.jinja
peakrdl_cheader-0.0.1.dist-info/LICENSE
peakrdl_cheader-0.0.1.dist-info/METADATA
peakrdl_cheader-0.0.1.dist-info/WHEEL
peakrdl_cheader-0.0.1.dist-info/entry_points.txt
peakrdl_cheader-0.0.1.dist-info/top_level.txt
peakrdl_cheader-0.0.1.dist-info/RECORD
