Metadata-Version: 2.1
Name: peakrdl-cheader
Version: 0.0.1
Summary: Generate c headers for register model compiled SystemRDL input
Home-page: https://github.com/krcb197/PeakRDL-CHeader
Author: Keith Brady
Project-URL: Source, https://github.com/krcb197/PeakRDL-cheader
Project-URL: Tracker, https://github.com/krcb197/PeakRDL-cheader/issues
Project-URL: Documentation, https://peakrdl-cheader.readthedocs.io/
Classifier: Development Status :: 4 - Beta
Classifier: Programming Language :: Python
Classifier: Programming Language :: Python :: 3
Classifier: Programming Language :: Python :: 3.7
Classifier: Programming Language :: Python :: 3.8
Classifier: Programming Language :: Python :: 3.9
Classifier: Programming Language :: Python :: 3.10
Classifier: Programming Language :: Python :: 3 :: Only
Classifier: Intended Audience :: Developers
Classifier: License :: OSI Approved :: GNU General Public License v3 (GPLv3)
Classifier: Operating System :: OS Independent
Classifier: Topic :: Scientific/Engineering :: Electronic Design Automation (EDA)
License-File: LICENSE
Requires-Dist: systemrdl-compiler (>=1.21.0)
Requires-Dist: jinja2
Requires-Dist: peakrdl-ipxact
